{
  "AWSTemplateFormatVersion": "2010-09-09",
  "Description": "{\"createdOn\":\"Mac\",\"createdBy\":\"Amplify\",\"createdWith\":\"14.0.2\",\"stackType\":\"api-API Gateway\",\"metadata\":{\"whyContinueWithGen1\":\"Prefer not to answer\"}}",
  "Parameters": {
    "functiongameHandlerName": {
      "Type": "String",
      "Default": "functiongameHandlerName"
    },
    "functiongameHandlerArn": {
      "Type": "String",
      "Default": "functiongameHandlerArn"
    },
    "env": {
      "Type": "String"
    }
  },
  "Conditions": {
    "ShouldNotCreateEnvResources": {
      "Fn::Equals": [
        {
          "Ref": "env"
        },
        "NONE"
      ]
    }
  },
  "Resources": {
    "westofhouseapi": {
      "Type": "AWS::ApiGateway::RestApi",
      "Properties": {
        "Description": "West of Haunted House Game API",
        "Name": {
          "Fn::If": [
            "ShouldNotCreateEnvResources",
            "westofhouseapi",
            {
              "Fn::Join": [
                "",
                [
                  "westofhouseapi",
                  "-",
                  {
                    "Ref": "env"
                  }
                ]
              ]
            }
          ]
        },
        "Tags": [
          {
            "Key": "Project",
            "Value": "west-of-haunted-house"
          },
          {
            "Key": "ManagedBy",
            "Value": "vedfolnir"
          },
          {
            "Key": "Environment",
            "Value": {
              "Ref": "env"
            }
          }
        ],
        "Body": {
          "swagger": "2.0",
          "info": {
            "version": "2018-05-24T17:52:00Z",
            "title": "westofhouseapi"
          },
          "host": {
            "Fn::Join": [
              "",
              [
                "apigateway.",
                {
                  "Ref": "AWS::Region"
                },
                ".amazonaws.com"
              ]
            ]
          },
          "basePath": {
            "Fn::If": [
              "ShouldNotCreateEnvResources",
              "/Prod",
              {
                "Fn::Join": [
                  "",
                  [
                    "/",
                    {
                      "Ref": "env"
                    }
                  ]
                ]
              }
            ]
          },
          "schemes": [
            "https"
          ],
          "paths": {
            "/game/new": {
              "options": {
                "consumes": [
                  "application/json"
                ],
                "produces": [
                  "application/json"
                ],
                "responses": {
                  "200": {
                    "description": "200 response",
                    "headers": {
                      "Access-Control-Allow-Origin": {
                        "type": "string"
                      },
                      "Access-Control-Allow-Methods": {
                        "type": "string"
                      },
                      "Access-Control-Allow-Headers": {
                        "type": "string"
                      }
                    }
                  }
                },
                "x-amazon-apigateway-integration": {
                  "responses": {
                    "default": {
                      "statusCode": "200",
                      "responseParameters": {
                        "method.response.header.Access-Control-Allow-Methods": "'DELETE,GET,HEAD,OPTIONS,PATCH,POST,PUT'",
                        "method.response.header.Access-Control-Allow-Headers": "'Content-Type,X-Amz-Date,Authorization,X-Api-Key,X-Amz-Security-Token,X-Amz-User-Agent'",
                        "method.response.header.Access-Control-Allow-Origin": "'*'"
                      }
                    }
                  },
                  "requestTemplates": {
                    "application/json": "{\"statusCode\": 200}"
                  },
                  "passthroughBehavior": "when_no_match",
                  "type": "mock"
                }
              },
              "post": {
                "consumes": [
                  "application/json"
                ],
                "produces": [
                  "application/json"
                ],
                "responses": {
                  "200": {
                    "description": "200 response",
                    "headers": {
                      "Access-Control-Allow-Origin": {
                        "type": "string"
                      }
                    }
                  }
                },
                "x-amazon-apigateway-integration": {
                  "responses": {
                    "default": {
                      "statusCode": "200",
                      "responseParameters": {
                        "method.response.header.Access-Control-Allow-Origin": "'*'"
                      }
                    }
                  },
                  "uri": {
                    "Fn::Join": [
                      "",
                      [
                        "arn:aws:apigateway:",
                        {
                          "Ref": "AWS::Region"
                        },
                        ":lambda:path/2015-03-31/functions/",
                        {
                          "Ref": "functiongameHandlerArn"
                        },
                        "/invocations"
                      ]
                    ]
                  },
                  "passthroughBehavior": "when_no_match",
                  "httpMethod": "POST",
                  "type": "aws_proxy"
                }
              }
            },
            "/game/command": {
              "options": {
                "consumes": [
                  "application/json"
                ],
                "produces": [
                  "application/json"
                ],
                "responses": {
                  "200": {
                    "description": "200 response",
                    "headers": {
                      "Access-Control-Allow-Origin": {
                        "type": "string"
                      },
                      "Access-Control-Allow-Methods": {
                        "type": "string"
                      },
                      "Access-Control-Allow-Headers": {
                        "type": "string"
                      }
                    }
                  }
                },
                "x-amazon-apigateway-integration": {
                  "responses": {
                    "default": {
                      "statusCode": "200",
                      "responseParameters": {
                        "method.response.header.Access-Control-Allow-Methods": "'DELETE,GET,HEAD,OPTIONS,PATCH,POST,PUT'",
                        "method.response.header.Access-Control-Allow-Headers": "'Content-Type,X-Amz-Date,Authorization,X-Api-Key,X-Amz-Security-Token,X-Amz-User-Agent'",
                        "method.response.header.Access-Control-Allow-Origin": "'*'"
                      }
                    }
                  },
                  "requestTemplates": {
                    "application/json": "{\"statusCode\": 200}"
                  },
                  "passthroughBehavior": "when_no_match",
                  "type": "mock"
                }
              },
              "post": {
                "consumes": [
                  "application/json"
                ],
                "produces": [
                  "application/json"
                ],
                "responses": {
                  "200": {
                    "description": "200 response",
                    "headers": {
                      "Access-Control-Allow-Origin": {
                        "type": "string"
                      }
                    }
                  }
                },
                "x-amazon-apigateway-integration": {
                  "responses": {
                    "default": {
                      "statusCode": "200",
                      "responseParameters": {
                        "method.response.header.Access-Control-Allow-Origin": "'*'"
                      }
                    }
                  },
                  "uri": {
                    "Fn::Join": [
                      "",
                      [
                        "arn:aws:apigateway:",
                        {
                          "Ref": "AWS::Region"
                        },
                        ":lambda:path/2015-03-31/functions/",
                        {
                          "Ref": "functiongameHandlerArn"
                        },
                        "/invocations"
                      ]
                    ]
                  },
                  "passthroughBehavior": "when_no_match",
                  "httpMethod": "POST",
                  "type": "aws_proxy"
                }
              }
            },
            "/game/state/{session_id}": {
              "options": {
                "consumes": [
                  "application/json"
                ],
                "produces": [
                  "application/json"
                ],
                "responses": {
                  "200": {
                    "description": "200 response",
                    "headers": {
                      "Access-Control-Allow-Origin": {
                        "type": "string"
                      },
                      "Access-Control-Allow-Methods": {
                        "type": "string"
                      },
                      "Access-Control-Allow-Headers": {
                        "type": "string"
                      }
                    }
                  }
                },
                "x-amazon-apigateway-integration": {
                  "responses": {
                    "default": {
                      "statusCode": "200",
                      "responseParameters": {
                        "method.response.header.Access-Control-Allow-Methods": "'DELETE,GET,HEAD,OPTIONS,PATCH,POST,PUT'",
                        "method.response.header.Access-Control-Allow-Headers": "'Content-Type,X-Amz-Date,Authorization,X-Api-Key,X-Amz-Security-Token,X-Amz-User-Agent'",
                        "method.response.header.Access-Control-Allow-Origin": "'*'"
                      }
                    }
                  },
                  "requestTemplates": {
                    "application/json": "{\"statusCode\": 200}"
                  },
                  "passthroughBehavior": "when_no_match",
                  "type": "mock"
                }
              },
              "get": {
                "consumes": [
                  "application/json"
                ],
                "produces": [
                  "application/json"
                ],
                "parameters": [
                  {
                    "name": "session_id",
                    "in": "path",
                    "required": true,
                    "type": "string"
                  }
                ],
                "responses": {
                  "200": {
                    "description": "200 response",
                    "headers": {
                      "Access-Control-Allow-Origin": {
                        "type": "string"
                      }
                    }
                  }
                },
                "x-amazon-apigateway-integration": {
                  "responses": {
                    "default": {
                      "statusCode": "200",
                      "responseParameters": {
                        "method.response.header.Access-Control-Allow-Origin": "'*'"
                      }
                    }
                  },
                  "uri": {
                    "Fn::Join": [
                      "",
                      [
                        "arn:aws:apigateway:",
                        {
                          "Ref": "AWS::Region"
                        },
                        ":lambda:path/2015-03-31/functions/",
                        {
                          "Ref": "functiongameHandlerArn"
                        },
                        "/invocations"
                      ]
                    ]
                  },
                  "passthroughBehavior": "when_no_match",
                  "httpMethod": "POST",
                  "type": "aws_proxy"
                }
              }
            }
          }
        },
        "FailOnWarnings": true
      }
    },
    "DeploymentAPIGW": {
      "Type": "AWS::ApiGateway::Deployment",
      "Properties": {
        "Description": "The Development stage deployment of your API.",
        "StageName": {
          "Fn::If": [
            "ShouldNotCreateEnvResources",
            "Prod",
            {
              "Ref": "env"
            }
          ]
        },
        "RestApiId": {
          "Ref": "westofhouseapi"
        }
      }
    },
    "APIGatewayStage": {
      "Type": "AWS::ApiGateway::Stage",
      "Properties": {
        "DeploymentId": {
          "Ref": "DeploymentAPIGW"
        },
        "RestApiId": {
          "Ref": "westofhouseapi"
        },
        "StageName": {
          "Fn::If": [
            "ShouldNotCreateEnvResources",
            "Prod",
            {
              "Ref": "env"
            }
          ]
        },
        "Tags": [
          {
            "Key": "Project",
            "Value": "west-of-haunted-house"
          },
          {
            "Key": "ManagedBy",
            "Value": "vedfolnir"
          },
          {
            "Key": "Environment",
            "Value": {
              "Ref": "env"
            }
          }
        ]
      }
    },
    "LambdaExecutionRole": {
      "Type": "AWS::IAM::Role",
      "Properties": {
        "RoleName": {
          "Fn::If": [
            "ShouldNotCreateEnvResources",
            "westofhouseapiLambdaRole",
            {
              "Fn::Join": [
                "",
                [
                  "westofhouseapiLambdaRole",
                  "-",
                  {
                    "Ref": "env"
                  }
                ]
              ]
            }
          ]
        },
        "AssumeRolePolicyDocument": {
          "Version": "2012-10-17",
          "Statement": [
            {
              "Effect": "Allow",
              "Principal": {
                "Service": [
                  "lambda.amazonaws.com"
                ]
              },
              "Action": [
                "sts:AssumeRole"
              ]
            }
          ]
        },
        "Tags": [
          {
            "Key": "Project",
            "Value": "west-of-haunted-house"
          },
          {
            "Key": "ManagedBy",
            "Value": "vedfolnir"
          },
          {
            "Key": "Environment",
            "Value": {
              "Ref": "env"
            }
          }
        ]
      }
    },
    "lambdaexecutionpolicy": {
      "DependsOn": [
        "LambdaExecutionRole"
      ],
      "Type": "AWS::IAM::Policy",
      "Properties": {
        "PolicyName": "lambda-execution-policy",
        "Roles": [
          {
            "Ref": "LambdaExecutionRole"
          }
        ],
        "PolicyDocument": {
          "Version": "2012-10-17",
          "Statement": [
            {
              "Effect": "Allow",
              "Action": [
                "logs:CreateLogGroup",
                "logs:CreateLogStream",
                "logs:PutLogEvents"
              ],
              "Resource": {
                "Fn::Sub": [
                  "arn:aws:logs:${region}:${account}:log-group:/aws/lambda/${lambda}:log-stream:*",
                  {
                    "region": {
                      "Ref": "AWS::Region"
                    },
                    "account": {
                      "Ref": "AWS::AccountId"
                    },
                    "lambda": {
                      "Ref": "functiongameHandlerName"
                    }
                  }
                ]
              }
            }
          ]
        }
      }
    },
    "gameHandlerInvokePermission": {
      "Type": "AWS::Lambda::Permission",
      "Properties": {
        "FunctionName": {
          "Ref": "functiongameHandlerName"
        },
        "Action": "lambda:InvokeFunction",
        "Principal": "apigateway.amazonaws.com",
        "SourceArn": {
          "Fn::Join": [
            "",
            [
              "arn:aws:execute-api:",
              {
                "Ref": "AWS::Region"
              },
              ":",
              {
                "Ref": "AWS::AccountId"
              },
              ":",
              {
                "Ref": "westofhouseapi"
              },
              "/*/*/*"
            ]
          ]
        }
      }
    }
  },
  "Outputs": {
    "RootUrl": {
      "Description": "Root URL of the API gateway",
      "Value": {
        "Fn::Join": [
          "",
          [
            "https://",
            {
              "Ref": "westofhouseapi"
            },
            ".execute-api.",
            {
              "Ref": "AWS::Region"
            },
            ".amazonaws.com/",
            {
              "Fn::If": [
                "ShouldNotCreateEnvResources",
                "Prod",
                {
                  "Ref": "env"
                }
              ]
            }
          ]
        ]
      }
    },
    "ApiName": {
      "Description": "API Friendly name",
      "Value": "westofhouseapi"
    },
    "ApiId": {
      "Description": "API ID (prefix of API URL)",
      "Value": {
        "Ref": "westofhouseapi"
      }
    }
  }
}